{
    "function": "bin.tune.main",
    "best": {
        "function": "bin.tabpfnv2_finetune.main",
        "gpus": [
            "NVIDIA A100-SXM4-80GB"
        ],
        "n_parameters": 7243978,
        "tuning_time": "0:11:47.477461",
        "trial_id": 5,
        "scores": {
            "train": 0.8074672610755085,
            "val": 0.8282608695652174,
            "test": 0.8226555246053854
        },
        "time": "0:01:48.907400"
    },
    "n_completed_trials": 10,
    "time": "0:19:42.353918"
}
